MANIFEST.in
README.rst
setup.py
libsongtext/__init__.py
libsongtext/errors.py
libsongtext/lyricwiki.py
libsongtext/properties.py
libsongtext/songtext.py
libsongtext/utils.py
songtext.egg-info/PKG-INFO
songtext.egg-info/SOURCES.txt
songtext.egg-info/dependency_links.txt
songtext.egg-info/entry_points.txt
songtext.egg-info/requires.txt
songtext.egg-info/top_level.txt
tests/__init__.py
tests/context.py
tests/test_api_integrations.py
tests/test_local_options.py