Metadata-Version: 1.1
Name: songtext
Version: 0.1.9
Summary: a command-line song lyric fetcher
Home-page: https://github.com/ysim/songtext
Author: ysim
Author-email: opensource@yiqingsim.net
License: BSD
Keywords: console command line music song lyrics
Platform: UNKNOWN
Classifier: Development Status :: 5 - Production/Stable
Classifier: Environment :: Console
Classifier: Operating System :: OS Independent
Classifier: License :: OSI Approved :: BSD License
Classifier: Programming Language :: Python
